cellqc/Snakefile
cellqc/__init__.py
cellqc/cellqc.py
cellqc/rules/common.smk
cellqc/rules/config.smk
cellqc/rules/doubletfinder.smk
cellqc/rules/dropkick.smk
cellqc/rules/filterbycount.smk
cellqc/rules/h5seurat2h5ad.smk
cellqc/rules/h5subset.smk
cellqc/rules/nuclear_fraction.smk
cellqc/rules/postproc.smk
cellqc/rules/qcreport.smk
cellqc/rules/scpred.smk
cellqc/rules/soupx.smk
cellqc/schemas/config.schema.yaml
cellqc/schemas/samples.schema.yaml
cellqc/scripts/doubletfinder.R
cellqc/scripts/dropkick.py
cellqc/scripts/filterbycount.R
cellqc/scripts/h5seurat2h5ad.R
cellqc/scripts/h5subset.R
cellqc/scripts/nuclear_fraction.R
cellqc/scripts/postproc.py
cellqc/scripts/qcreport.py
cellqc/scripts/scpred.R
cellqc/scripts/soupx.R
cellqc/scripts/template/index.html.jinja2
cellqc/scripts/template/style.css
cellqc-0.1.0.dist-info/LICENSE
cellqc-0.1.0.dist-info/METADATA
cellqc-0.1.0.dist-info/WHEEL
cellqc-0.1.0.dist-info/entry_points.txt
cellqc-0.1.0.dist-info/top_level.txt
cellqc-0.1.0.dist-info/RECORD
