Metadata-Version: 2.1
Name: cellqc
Version: 0.1.0
Summary: Cellqc standardizes the qualiy control of single-cell RNA-Seq (scRNA) data to render clean feature count matrices.
Home-page: https://github.com/lijinbio/cellqc
Author: Jin Li
Author-email: lijin.abc@gmail.com
License: MIT license
Classifier: Development Status :: 2 - Pre-Alpha
Classifier: License :: OSI Approved :: MIT License
Classifier: Natural Language :: English
Classifier: Programming Language :: Python :: 3
Requires-Python: >=3.6
License-File: LICENSE
Requires-Dist: click
Requires-Dist: snakemake
Requires-Dist: pygraphviz
Requires-Dist: Jinja2
